{
  "RSpec": {
    "coverage": {
      "/Users/megangosnell/Desktop/MakersBnB/spec/spaces_spec.rb": {
        "lines": [
          1,
          null,
          1,
          null,
          1,
          1,
          1,
          1,
          1,
          null,
          null,
          null
        ]
      },
      "/Users/megangosnell/Desktop/MakersBnB/lib/spaces.rb": {
        "lines": [
          null,
          1,
          1,
          1,
          1,
          null,
          null,
          1,
          1,
          null,
          null,
          null
        ]
      }
    },
    "timestamp": 1612263042
  }
}
